yolov5_utils/__init__.py
yolov5_utils/__version__.py
yolov5_utils/cli.py
yolov5_utils/helpers.py
yolov5_utils/import_hook.py
yolov5_utils/yolov5/CITATION.cff
yolov5_utils/yolov5/CONTRIBUTING.md
yolov5_utils/yolov5/LICENSE
yolov5_utils/yolov5/README.md
yolov5_utils/yolov5/README.zh-CN.md
yolov5_utils/yolov5/__init__.py
yolov5_utils/yolov5/benchmarks.py
yolov5_utils/yolov5/detect.py
yolov5_utils/yolov5/export.py
yolov5_utils/yolov5/hubconf.py
yolov5_utils/yolov5/requirements.txt
yolov5_utils/yolov5/setup.cfg
yolov5_utils/yolov5/train.py
yolov5_utils/yolov5/tutorial.ipynb
yolov5_utils/yolov5/val.py
yolov5_utils/yolov5/classify/predict.py
yolov5_utils/yolov5/classify/train.py
yolov5_utils/yolov5/classify/tutorial.ipynb
yolov5_utils/yolov5/classify/val.py
yolov5_utils/yolov5/data/Argoverse.yaml
yolov5_utils/yolov5/data/GlobalWheat2020.yaml
yolov5_utils/yolov5/data/ImageNet.yaml
yolov5_utils/yolov5/data/Objects365.yaml
yolov5_utils/yolov5/data/SKU-110K.yaml
yolov5_utils/yolov5/data/VOC.yaml
yolov5_utils/yolov5/data/VisDrone.yaml
yolov5_utils/yolov5/data/coco.yaml
yolov5_utils/yolov5/data/coco128-seg.yaml
yolov5_utils/yolov5/data/coco128.yaml
yolov5_utils/yolov5/data/xView.yaml
yolov5_utils/yolov5/data/hyps/hyp.Objects365.yaml
yolov5_utils/yolov5/data/hyps/hyp.VOC.yaml
yolov5_utils/yolov5/data/hyps/hyp.no-augmentation.yaml
yolov5_utils/yolov5/data/hyps/hyp.scratch-high.yaml
yolov5_utils/yolov5/data/hyps/hyp.scratch-low.yaml
yolov5_utils/yolov5/data/hyps/hyp.scratch-med.yaml
yolov5_utils/yolov5/data/images/bus.jpg
yolov5_utils/yolov5/data/images/zidane.jpg
yolov5_utils/yolov5/data/scripts/download_weights.sh
yolov5_utils/yolov5/data/scripts/get_coco.sh
yolov5_utils/yolov5/data/scripts/get_coco128.sh
yolov5_utils/yolov5/data/scripts/get_imagenet.sh
yolov5_utils/yolov5/models/__init__.py
yolov5_utils/yolov5/models/common.py
yolov5_utils/yolov5/models/experimental.py
yolov5_utils/yolov5/models/tf.py
yolov5_utils/yolov5/models/yolo.py
yolov5_utils/yolov5/models/yolov5l.yaml
yolov5_utils-7.1.5.dist-info/LICENSE
yolov5_utils-7.1.5.dist-info/METADATA
yolov5_utils-7.1.5.dist-info/WHEEL
yolov5_utils-7.1.5.dist-info/entry_points.txt
yolov5_utils-7.1.5.dist-info/top_level.txt
yolov5_utils-7.1.5.dist-info/RECORD
